synthesized/__init__.py
synthesized/api.cp38-win_amd64.pyd
synthesized/api.py
synthesized/cmd_line.cp38-win_amd64.pyd
synthesized/cmd_line.py
synthesized/config.py
synthesized/config_schema.yaml
synthesized/version.cp38-win_amd64.pyd
synthesized/version.py
synthesized/_licence/__init__.py
synthesized/_licence/analytics.cp38-win_amd64.pyd
synthesized/_licence/analytics.py
synthesized/_licence/exceptions.cp38-win_amd64.pyd
synthesized/_licence/exceptions.py
synthesized/_licence/features.cp38-win_amd64.pyd
synthesized/_licence/features.py
synthesized/_licence/gcloud.cp38-win_amd64.pyd
synthesized/_licence/gcloud.py
synthesized/_licence/licence.cp38-win_amd64.pyd
synthesized/_licence/licence.py
synthesized/_licence/prompt.cp38-win_amd64.pyd
synthesized/_licence/prompt.py
synthesized/common/__init__.py
synthesized/common/binary_builder.cp38-win_amd64.pyd
synthesized/common/binary_builder.py
synthesized/common/check.cp38-win_amd64.pyd
synthesized/common/check.py
synthesized/common/differential_privacy.cp38-win_amd64.pyd
synthesized/common/differential_privacy.py
synthesized/common/module.cp38-win_amd64.pyd
synthesized/common/module.py
synthesized/common/synthesizer.cp38-win_amd64.pyd
synthesized/common/synthesizer.py
synthesized/common/util.cp38-win_amd64.pyd
synthesized/common/util.py
synthesized/common/encodings/__init__.py
synthesized/common/encodings/encoding.cp38-win_amd64.pyd
synthesized/common/encodings/encoding.py
synthesized/common/encodings/variational.cp38-win_amd64.pyd
synthesized/common/encodings/variational.py
synthesized/common/generative/__init__.py
synthesized/common/generative/engine.cp38-win_amd64.pyd
synthesized/common/generative/engine.py
synthesized/common/generative/generative.cp38-win_amd64.pyd
synthesized/common/generative/generative.py
synthesized/common/generative/mock.cp38-win_amd64.pyd
synthesized/common/generative/mock.py
synthesized/common/generative/state_space.cp38-win_amd64.pyd
synthesized/common/generative/state_space.py
synthesized-2.24.dist-info/LICENSE.md
synthesized-2.24.dist-info/METADATA
synthesized-2.24.dist-info/WHEEL
synthesized-2.24.dist-info/entry_points.txt
synthesized-2.24.dist-info/top_level.txt
synthesized-2.24.dist-info/RECORD
