Metadata-Version: 2.1
Name: synthesized
Version: 2.24
Summary: Synthesized SDK
Author-email: "Synthesized Ltd." <sdk-team@synthesized.io>
License: Copyright 2018 Synthesized LTD
Project-URL: homepage, https://synthesized.io
Project-URL: documentation, https://docs.synthesized.io/
Project-URL: repository, https://github.com/synthesized-io/synthesized-sdk
Keywords: synthetic,generative,data
Platform: MacOS
Platform: Windows
Platform: Linux
Classifier: Development Status :: 5 - Production/Stable
Classifier: License :: Other/Proprietary License
Classifier: Intended Audience :: Developers
Classifier: Intended Audience :: Financial and Insurance Industry
Classifier: Intended Audience :: Information Technology
Classifier: Intended Audience :: Healthcare Industry
Classifier: Operating System :: MacOS
Classifier: Operating System :: Microsoft :: Windows
Classifier: Operating System :: POSIX
Classifier: Operating System :: Unix
Classifier: Programming Language :: Python :: 3
Classifier: Programming Language :: Python :: 3 :: Only
Classifier: Programming Language :: Python :: 3.8
Classifier: Programming Language :: Python :: 3.9
Classifier: Programming Language :: Python :: 3.10
Classifier: Programming Language :: Python :: 3.11
Classifier: Programming Language :: Python :: Implementation :: CPython
Classifier: Topic :: Scientific/Engineering
Classifier: Topic :: Scientific/Engineering :: Artificial Intelligence
Requires-Python: <3.12,>=3.8
License-File: LICENSE.md
Requires-Dist: Babel>=2.2.1
Requires-Dist: cleanco>=2.2
Requires-Dist: faker>=18.0.0
Requires-Dist: matplotlib<3.8,>=3.4
Requires-Dist: numpy>=1.19.2
Requires-Dist: pandas<2.0,>=1.3
Requires-Dist: prompt-toolkit>=3.0
Requires-Dist: psutil>=5.0
Requires-Dist: PyYAML>=5.2
Requires-Dist: rsa>=4.7
Requires-Dist: rstr>=2.2
Requires-Dist: scikit-learn<1.4,>=0.23
Requires-Dist: scipy<1.12,>=1.5
Requires-Dist: seaborn>=0.11
Requires-Dist: synthesized-insight>=0.5
Requires-Dist: typo>=0.1.7
Requires-Dist: yamale>=4.0.4
Requires-Dist: tensorflow<2.15.0,>=2.6.2; platform_machine != "arm64" or platform_system != "Darwin"
Requires-Dist: tensorflow-macos<2.15.0,>=2.6; platform_machine == "arm64" and platform_system == "Darwin"
Requires-Dist: faker<37.11.0; python_version < "3.10"
Requires-Dist: urllib3<2.0; python_version < "3.8"
Provides-Extra: dev
Requires-Dist: pre-commit; extra == "dev"
Requires-Dist: black; extra == "dev"
Requires-Dist: mypy; extra == "dev"
Requires-Dist: pylint; extra == "dev"
Provides-Extra: dp
Requires-Dist: tensorflow-privacy<0.8,>=0.6; extra == "dp"
Requires-Dist: tensorflow-probability<0.19.0,>=0.14.0; extra == "dp"
Requires-Dist: tensorflow<2.11,>=2.6.2; (platform_machine != "arm64" or platform_system != "Darwin") and extra == "dp"
Requires-Dist: tensorflow-macos<2.11,>=2.6; (platform_machine == "arm64" and platform_system == "Darwin") and extra == "dp"
Provides-Extra: gcloud
Requires-Dist: google-cloud-service-control>=1.9; extra == "gcloud"
Provides-Extra: test
Requires-Dist: pytest; extra == "test"
Requires-Dist: pytest-cov; extra == "test"
Requires-Dist: synthesized-datasets>=1.5; extra == "test"
Requires-Dist: hypothesis[pandas]; extra == "test"
Requires-Dist: pytest-httpserver; extra == "test"
Requires-Dist: h5py<3.15; extra == "test"
Provides-Extra: tune
Requires-Dist: ray[tune]; extra == "tune"
Requires-Dist: ax-platform<0.3.7; extra == "tune"
